lobe/__init__.py
lobe/api_client.py
lobe/api_constants.py
lobe/image_utils.py
lobe/results.py
lobe/signature.py
lobe/signature_constants.py
lobe/utils.py
lobe/backends/__init__.py
lobe/backends/backend.py
lobe/backends/onnx/__init__.py
lobe/backends/onnx/backend.py
lobe/backends/onnx/image_backend.py
lobe/backends/tf/__init__.py
lobe/backends/tf/backend.py
lobe/backends/tf/image_backend.py
lobe/backends/tflite/__init__.py
lobe/backends/tflite/backend.py
lobe/backends/tflite/image_backend.py
lobe/model/__init__.py
lobe/model/image_model.py
lobe/model/model.py
lobe-0.6.2.dist-info/LICENSE
lobe-0.6.2.dist-info/METADATA
lobe-0.6.2.dist-info/WHEEL
lobe-0.6.2.dist-info/top_level.txt
lobe-0.6.2.dist-info/RECORD
